nonebot_plugin_rimofun-0.3.0.dist-info/METADATA
nonebot_plugin_rimofun-0.3.0.dist-info/WHEEL
nonebot_plugin_rimofun-0.3.0.dist-info/licenses/LICENSE
nonebot_plugin_rimofun/__init__.py
nonebot_plugin_rimofun/__main__.py
nonebot_plugin_rimofun/bnhhsh/.git
nonebot_plugin_rimofun/bnhhsh/LICENSE
nonebot_plugin_rimofun/bnhhsh/bnhhsh/__init__.py
nonebot_plugin_rimofun/bnhhsh/bnhhsh/data/常用汉字.json
nonebot_plugin_rimofun/bnhhsh/bnhhsh/data/现代汉语常用词表.json
nonebot_plugin_rimofun/bnhhsh/bnhhsh/data/色情词库.json
nonebot_plugin_rimofun/bnhhsh/bnhhsh/data/色情词库_数据增强.json
nonebot_plugin_rimofun/bnhhsh/bnhhsh/data/莉沫词库.json
nonebot_plugin_rimofun/bnhhsh/img/s.jpg
nonebot_plugin_rimofun/bnhhsh/readme.md
nonebot_plugin_rimofun/bnhhsh/setup.py
nonebot_plugin_rimofun/config.py
nonebot_plugin_rimofun/data_source.py
nonebot_plugin_rimofun/not_translator/.git
nonebot_plugin_rimofun/not_translator/not_translator/__init__.py
nonebot_plugin_rimofun/not_translator/not_translator/ipa_data/en_US.txt
nonebot_plugin_rimofun/not_translator/not_translator/ipa_data/zh_hans.txt
nonebot_plugin_rimofun/not_translator/not_translator/常用汉字.json
nonebot_plugin_rimofun/not_translator/not_translator/摸型.json
nonebot_plugin_rimofun/not_translator/readme.md
nonebot_plugin_rimofun/not_translator/训练代码/data/名字.json
nonebot_plugin_rimofun/not_translator/训练代码/数据.py
nonebot_plugin_rimofun/not_translator/训练代码/超.py
nonebot_plugin_rimofun-0.3.0.dist-info/RECORD
