Metadata-Version: 2.1
Name: nonebot-plugin-rimofun
Version: 0.3.0
Summary: Use RimoChan's stuff to do some interesting things
Home-page: https://github.com/lgc-NB2Dev/nonebot-plugin-rimofun
Author-Email: student_2333 <lgc2333@126.com>
License: MIT
Project-URL: Homepage, https://github.com/lgc-NB2Dev/nonebot-plugin-rimofun
Requires-Python: <4.0,>=3.9
Requires-Dist: nonebot2>=2.2.0
Requires-Dist: nonebot-plugin-alconna>=0.40.0rc1
Requires-Dist: pypinyin>=0.48.0
Requires-Dist: yinglish>=1.0.1
Requires-Dist: unvcode>=1.0.0
